arlatentsde/__init__.py
arlatentsde/autoencoders.py
arlatentsde/data.py
arlatentsde/elbo.py
arlatentsde/integrate.py
arlatentsde/kernels.py
arlatentsde/latent_sdes.py
arlatentsde/lit_model.py
arlatentsde/monte_carlo.py
arlatentsde/plotting/__init__.py
arlatentsde/plotting/_plotting.py
arlatentsde/priors/__init__.py
arlatentsde/priors/_priors.py
arlatentsde/priors/variationalsparsebayes/__init__.py
arlatentsde/priors/variationalsparsebayes/sparse_glm.py
arlatentsde/priors/variationalsparsebayes/svi_half_cauchy.py
arlatentsde/types.py
arlatentsde-0.2.0.dist-info/LICENSE
arlatentsde-0.2.0.dist-info/METADATA
arlatentsde-0.2.0.dist-info/WHEEL
arlatentsde-0.2.0.dist-info/RECORD
