Metadata-Version: 2.1
Name: arlatentsde
Version: 0.2.0
Summary: Amortized Reparametrization for Continuous Time Autoencoders (ARCTA)
License: GNUv3
Author: Kevin Course
Requires-Python: >=3.10,<3.12
Classifier: License :: Other/Proprietary License
Classifier: Programming Language :: Python :: 3
Classifier: Programming Language :: Python :: 3.10
Classifier: Programming Language :: Python :: 3.11
Requires-Dist: beartype (>=0.12.0,<0.13.0)
Requires-Dist: jaxtyping (>=0.2.14,<0.3.0)
Requires-Dist: pytorch-lightning (>=2.0.1.post0,<3.0.0)
Requires-Dist: tensorboard (>=2.12.1,<3.0.0)
Requires-Dist: torch (>=2.0.1,<3.0.0)
Requires-Dist: torchaudio (>=2.0.2,<3.0.0)
Requires-Dist: torchdiffeq (>=0.2.3,<0.3.0)
Requires-Dist: torchsde (>=0.2.5,<0.3.0)
Requires-Dist: torchvision (>=0.15.2,<0.16.0)
